Metadata-Version: 2.1
Name: imdb-scrape-top-movies
Version: 1.0.3
Summary: A python library to search top movies on imdb
Home-page: UNKNOWN
Author: DataKund
Author-email: datakund@gmail.com
License: Apache License 2.0
Keywords: imdb python bot_studio automation movies top-movies movie-rating movie-title
Platform: UNKNOWN
License-File: LICENSE
